<?xml version="1.0" encoding="UTF-8"?>
<!--curve-fitting-strings_nl.xml created Mon May 18 07:29:15 CEST 2009 using: curve-fitting 2.00.00 (30671), translation-utility 2.00.00 (31012) apr 28, 2009-->
<SimStrings>
<string key="clearAll" value="Wis alles"/>
<string key="deviations" value="toon deviaties"/>
<string key="quartic" value="Vierdegraads"/>
<string key="simTitle" value="Functie van een grafiek bepalen"/>
<string key="bestFit" value="Best passend"/>
<string key="quadratic" value="Kwadratisch"/>
<string key="bucketHelp2" value="of zet ze terug."/>
<string key="bucketHelp1" value="Plaats meetpunten..."/>
<string key="cubic" value="derdegraads"/>
<string key="noFit" value="Geen fit"/>
<string key="adjustableFit2" value="Zelf aanpassen"/>
<string key="dataPointHelp" value="balken van afwijking verslepen"/>
<string key="bestFit2" value="Best passend:"/>
<string key="hideHelp" value="Verberg help"/>
<string key="correlation" value="correlatie coëfficient "/>
<string key="chiSqHelp5" value=":   fit te goed   (afwijking te klein)"/>
<string key="bucketLabel" value="Meet-     punten"/>
<string key="chiSqHelp4" value=":   goede fit   (groene zone)"/>
<string key="chiSqHelp3" value=":   slechte fit   (rode zone)"/>
<string key="chiSqHelp2" value="N = aantal meetpunten \n f = aantal parameters in fit  \n ( f = 4 voor een derdegraadsfit )"/>
<string key="chiSqHelp1" value="De gereduceerde chi-kwadraatfunctie is"/>
<string key="adjustableFit" value="Zelf aanpassen"/>
<string key="linear" value="Liniair"/>
</SimStrings>
