<?xml version="1.0" encoding="UTF-8" standalone="no"?>
<!--blackbody-spectrum-strings_ja.xml created Mon Sep 06 17:51:39 JST 2010 using: blackbody-spectrum 2.01.00 (39582), translation-utility 2.08.00 (39581) 4 2, 2010-->
<SimStrings>
<string key="r" value="赤"/>
<string key="zoomIn" value="ズーム \n イン"/>
<string key="intensity" value="強度"/>
<string key="simTitle" value="黒体のスペクトル(Blackbody Spectrum)"/>
<string key="zoomOut" value="ズーム \n アウト"/>
<string key="clear" value="クリア"/>
<string key="g" value="緑"/>
<string key="sun" value="太陽"/>
<string key="tempInK" value="T(K)"/>
<string key="save" value="保存"/>
<string key="showRuler" value="メジャーを表示"/>
<string key="wavelength" value="波長"/>
<string key="b" value="青"/>
<string key="oven" value="オーブンレンジ"/>
<string key="earth" value="地球"/>
<string key="lightBulb" value="白熱電球"/>
</SimStrings>
