<?xml version="1.0" encoding="UTF-8" standalone="no"?>
<!--collision-lab-strings_zh_CN.xml created Wed Apr 06 14:02:52 CST 2011 using: collision-lab 0.01.00 (45337), translation-utility 2.10.00 (48775) 二月 9, 2011-->
<SimStrings>
<string key="PlayPauseButtons.step" value="微调前进"/>
<string key="MomentumView.total" value="合计"/>
<string key="ControlPanel.sound" value="声音"/>
<string key="ControlPanel.showMomentumVectors" value="动量矢量"/>
<string key="ControlPanel.oneHundredPercent" value="100%"/>
<string key="DataTable.lessData" value="较少的数据"/>
<string key="translation.credits" value="张大红"/>
<string key="MomentumView.momenta" value="动量"/>
<string key="DataTable.ball" value="球"/>
<string key="TableView.kineticEnergy" value="动能={0}焦耳"/>
<string key="ControlPanel.showVelocities" value="速度矢量"/>
<string key="ControlPanel.showPaths" value="显示路径"/>
<string key="DataTable.mass" value="质量"/>
<string key="DataTable.addBall" value="加球"/>
<string key="DataTable.py" value="y坐标"/>
<string key="DataTable.px" value="x坐标"/>
<string key="PlayPauseButtons.pause" value="暂停"/>
<string key="DataTable.vy" value="Vy"/>
<string key="DataTable.vx" value="Vx"/>
<string key="ControlPanel.2d" value="二维"/>
<string key="DataTable.moreData" value="更多数据"/>
<string key="ControlPanel.reflectingBorder" value="反射边界"/>
<string key="DataTable.y" value="y"/>
<string key="DataTable.removeBall" value="移除所有"/>
<string key="DataTable.x" value="x"/>
<string key="ControlPanel.resetAll" value="重设所有"/>
<string key="ControlPanel.momentaDiagram" value="动量图"/>
<string key="ControlPanel.elasticity" value="弹性系数"/>
<string key="ControlPanel.showCenterOfMass" value="质心"/>
<string key="ControlPanel.zeroPercent" value="0%"/>
<string key="TableView.timeRate" value="时间变化率"/>
<string key="simTitle" value="碰撞实验室"/>
<string key="PlayPauseButtons.play" value="播放"/>
<string key="PlayPauseButtons.back" value="返回"/>
<string key="MomentumView.tipToTail" value="矢量合成图"/>
<string key="TableView.time" value="时间= {0} 秒"/>
<string key="PlayPauseButtons.rewind" value="倒带"/>
<string key="ControlPanel.1d" value="一维"/>
</SimStrings>
