<?xml version="1.0" ?>
<SimStrings>
  <string key="altitude" value="altitude(m)" />
  <string key="range" value="range(m)" />
  <string key="vY" value="v_y(m/s" />
  <string key="vX" value="v_x(m/s)" />
  <string key="vY" value="v_y(m/s)" />
  <string key="thrust" value="thrust(N)" />
  <string key="fuel" value="fuel(kg)" />
  <string key="full" value="F" />
  <string key="empty" value="E" />
  <string key="sound" value="Sound" />
  <string key="vectors" value="Vectors" />
  <string key="score" value="score:" />
  <string key="help" value="Help/Pause" />
  <string key="unpause" value="Unpause" />
  <string key="reset" value="Reset" />
  <string key="label1" value="Control the lander with keyboard" />
  <string key="label2" value="More Thrust" />
  <string key="label3" value="Tilt Left" />
  <string key="label4" value="Less Thrust" />
  <string key="label5" value="Tilt Right" />
  <string key="label6" value="Space Bar = Toggle Full Thrust" />
  <string key="start" value="Start" />
  <string key="label7" value="How many flat zones can you touch before fuel is out? \nExtra points for soft landings(v &lt; 2 m/s). \nGame over if you hit a boulder or crashland (v &gt; 6 m/s)." />
  <string key="paused" value="Paused" />
  <string key="softLandingsColon" value="soft landings:" />
  <string key="hardLandingsColon" value="hard landings:" />
  <string key="landingSpeedEq" value="Landing speed = " />
  <string key="softLanding" value="Soft Landing." />
  <string key="hardLanding" value="Hard Landing" />
  <string key="crash1" value="Crash landing, legs damaged." />
  <string key="crash2" value="Crash landing, crew killed." />
  <string key="hitBoulder" value="Hit boulder. \nLeg damaged. \nFuel lost." />
  <string key="help1" value="Keyboard Controls:" />
  <string key="help2" value="Reset" />
  <string key="help3" value="Pause" />
  <string key="r" value="R" />
  <string key="p" value="P" />
  <string key="velVector" value="Velocity vector" />
  <string key="accVector" value="Acceleration vector" />
  <string key="longHelp" value="~ Land in as many different flat zones as you can before your fuel runs out.\n~ After landing, take off by increasing thrust.\n~ No credit for landing in the same zone more than once.\n~ More points for landing in smaller or harder-to-reach zones:  \n     Easy big zones = 5 points   to    Killer tight zones = 50 points\n~ 10 extra points for a soft landing ( v &lt; 2 m/s).\n~ Game over if you touch a boulder. (You can't land on boulders!)\n~ Game over if you crash land (v &gt; 12 m/s)." />
  <string key="simTitle" value="Lunar Lander" />

</SimStrings>